"seachad/__init__,py"
seachad/calcs/__init__.py
seachad/calcs/calc.py
seachad/calcs/consts.py
seachad/common_libraries/IPL.py
seachad/common_libraries/__init__.py
seachad/common_libraries/ar_decorator_functions.py
seachad/common_libraries/cache_REDIS.py
seachad/common_libraries/common.py
seachad/common_libraries/resolve_fstring.py
seachad/common_libraries/terminal_colors.py
seachad-0.1.34.dist-info/METADATA
seachad-0.1.34.dist-info/WHEEL
seachad-0.1.34.dist-info/licenses/LICENSE
seachad-0.1.34.dist-info/RECORD
