Metadata-Version: 2.3
Name: seachad
Version: 0.1.34
Summary: Common packages from SEACHAD
Project-URL: Homepage, https://github.com/seachad/seachad
Project-URL: Bug Tracker, https://github.com/seachad/seachad/issues
Author-email: jovenluke <fernando.garcia.varela@outlook.es>
License: MIT License
License-File: LICENSE
Classifier: License :: OSI Approved :: MIT License
Classifier: Operating System :: OS Independent
Classifier: Programming Language :: Python :: 3
Requires-Python: >=3.10
Requires-Dist: colorama
Requires-Dist: cryptography
Requires-Dist: filelock
Requires-Dist: pandas
Requires-Dist: pycryptodome
Requires-Dist: python-dotenv
Requires-Dist: redis
Requires-Dist: retrying
